{
  "worldId": "cultivation",
  "type": "location_seed_pool",
  "localization": "docs/mvp-content-pool-draft.md#cultivation-world",
  "locations": [
    { "id": "mortal_birth_village", "nameKey": "cultivation.location.mortal_birth_village.name", "lifeStages": ["birth", "childhood"], "sceneTags": ["family", "ordinary_life", "mortal"], "accessTags": ["birthplace", "family"], "riskLevel": "low", "eventHooks": ["family_test", "wandering_cultivator"], "factionHooks": ["red_dust_merchant_house"], "aiUseRuleKey": "cultivation.location.mortal_birth_village" },
    { "id": "sect_outer_courtyard", "nameKey": "cultivation.location.sect_outer_courtyard.name", "lifeStages": ["adolescence", "youth", "adulthood"], "sceneTags": ["sect", "training", "competition"], "accessTags": ["outer_disciple", "servant", "guest"], "riskLevel": "medium", "eventHooks": ["spiritual_root_test", "outer_disciple_trial"], "factionHooks": ["azure_cloud_sect"], "aiUseRuleKey": "cultivation.location.sect_outer_courtyard" },
    { "id": "spirit_root_hall", "nameKey": "cultivation.location.spirit_root_hall.name", "lifeStages": ["childhood", "adolescence"], "sceneTags": ["test", "talent_exposure", "family_pressure"], "accessTags": ["test_candidate", "clan_child"], "riskLevel": "medium", "eventHooks": ["spiritual_root_test", "talent_exposure"], "factionHooks": ["azure_cloud_sect", "river_sword_clan"], "aiUseRuleKey": "cultivation.location.spirit_root_hall" },
    { "id": "green_bamboo_forest", "nameKey": "cultivation.location.green_bamboo_forest.name", "lifeStages": ["childhood", "adolescence", "youth"], "sceneTags": ["forest", "spirit_beast", "chance"], "accessTags": ["near_home", "trial"], "riskLevel": "medium", "eventHooks": ["herb_gathering", "beast_encounter"], "factionHooks": ["hidden_medicine_valley"], "aiUseRuleKey": "cultivation.location.green_bamboo_forest" },
    { "id": "wandering_market_square", "nameKey": "cultivation.location.wandering_market_square.name", "lifeStages": ["youth", "adulthood", "middleAge"], "sceneTags": ["market", "auction", "information"], "accessTags": ["traveler", "merchant", "disciple"], "riskLevel": "medium", "eventHooks": ["auction_odd_item", "merchant_deal"], "factionHooks": ["wandering_cultivator_market", "red_dust_merchant_house"], "aiUseRuleKey": "cultivation.location.wandering_market_square" },
    { "id": "ancient_cave_dwelling", "nameKey": "cultivation.location.ancient_cave_dwelling.name", "lifeStages": ["youth", "adulthood"], "sceneTags": ["inheritance", "danger", "secret"], "accessTags": ["map", "chance_encounter", "trial"], "riskLevel": "high", "eventHooks": ["inheritance_fragment", "array_trap"], "factionHooks": ["star_observation_tower"], "aiUseRuleKey": "cultivation.location.ancient_cave_dwelling" },
    { "id": "clan_ancestral_hall", "nameKey": "cultivation.location.clan_ancestral_hall.name", "lifeStages": ["childhood", "adolescence", "youth", "adulthood"], "sceneTags": ["family_clan", "bloodline", "inheritance"], "accessTags": ["bloodline", "family_guest"], "riskLevel": "medium", "eventHooks": ["ancestral_tablet_reaction", "marriage_alliance"], "factionHooks": ["river_sword_clan"], "aiUseRuleKey": "cultivation.location.clan_ancestral_hall" },
    { "id": "imperial_border_pass", "nameKey": "cultivation.location.imperial_border_pass.name", "lifeStages": ["youth", "adulthood", "middleAge"], "sceneTags": ["official", "war", "travel"], "accessTags": ["traveler", "official", "escort"], "riskLevel": "high", "eventHooks": ["beast_tide_warning", "official_mission"], "factionHooks": ["imperial_offering_office"], "aiUseRuleKey": "cultivation.location.imperial_border_pass" },
    { "id": "forbidden_lotus_shrine", "nameKey": "cultivation.location.forbidden_lotus_shrine.name", "lifeStages": ["youth", "adulthood"], "sceneTags": ["forbidden", "demonic_path", "temptation"], "accessTags": ["secret_map", "desperation", "cult_contact"], "riskLevel": "extreme", "eventHooks": ["demonic_invitation", "forbidden_art"], "factionHooks": ["black_lotus_cult"], "aiUseRuleKey": "cultivation.location.forbidden_lotus_shrine" },
    { "id": "medicine_valley_gate", "nameKey": "cultivation.location.medicine_valley_gate.name", "lifeStages": ["childhood", "adolescence", "youth", "adulthood"], "sceneTags": ["healing", "alchemy", "hidden_refuge"], "accessTags": ["rescued", "herb_debt", "healer_contact"], "riskLevel": "medium", "eventHooks": ["injury_recovery", "alchemy_apprentice"], "factionHooks": ["hidden_medicine_valley"], "aiUseRuleKey": "cultivation.location.medicine_valley_gate" }
  ]
}
