{
  "worldId": "wasteland",
  "type": "faction_seed_pool",
  "localization": "docs/mvp-content-pool-draft.md#wasteland-survival-world",
  "factions": [
    { "id": "rust_gate_camp", "nameKey": "wasteland.faction.rust_gate_camp.name", "typeTags": ["camp", "settlement", "defensive"], "routeTags": ["survival", "community", "leadership"], "riskLevel": "medium", "joinRequirementTags": ["birth_camp", "work_quota", "sponsor"], "creationRequirementTags": ["water_source", "walls", "defense_group"], "resourceTags": ["shelter", "ration", "guards"], "conflictTags": ["raiders", "water_tax", "internal_power"], "startingRelationship": { "attention": [0, 35], "trust": [-10, 25] }, "aiUseRuleKey": "wasteland.faction.rust_gate_camp" },
    { "id": "dry_well_caravan", "nameKey": "wasteland.faction.dry_well_caravan.name", "typeTags": ["caravan", "trade", "mobile"], "routeTags": ["travel", "trade", "rumor"], "riskLevel": "medium", "joinRequirementTags": ["useful_skill", "trade_debt", "escort_contract"], "creationRequirementTags": ["vehicles", "route_maps", "trade_goods"], "resourceTags": ["trade", "transport", "news"], "conflictTags": ["raiders", "camp_tariffs", "radiation_zone"], "startingRelationship": { "attention": [0, 30], "trust": [-10, 20] }, "aiUseRuleKey": "wasteland.faction.dry_well_caravan" },
    { "id": "bone_flag_raiders", "nameKey": "wasteland.faction.bone_flag_raiders.name", "typeTags": ["raiders", "violent", "mobile"], "routeTags": ["violence", "fear", "plunder"], "riskLevel": "extreme", "joinRequirementTags": ["captured", "outcast", "violent_reputation"], "creationRequirementTags": ["armed_followers", "fear_reputation", "hidden_garage"], "resourceTags": ["weapons", "loot", "vehicles"], "conflictTags": ["camp_militia", "caravan", "revenge"], "startingRelationship": { "attention": [10, 55], "trust": [-45, 5] }, "aiUseRuleKey": "wasteland.faction.bone_flag_raiders" },
    { "id": "greenhouse_collective", "nameKey": "wasteland.faction.greenhouse_collective.name", "typeTags": ["farm", "technology", "settlement"], "routeTags": ["food", "science", "community"], "riskLevel": "medium", "joinRequirementTags": ["agriculture_skill", "repair_skill", "refugee_screening"], "creationRequirementTags": ["seeds", "water_filter", "greenhouse_shell"], "resourceTags": ["food", "medicine", "seeds"], "conflictTags": ["water_raid", "tech_theft", "disease"], "startingRelationship": { "attention": [0, 30], "trust": [0, 30] }, "aiUseRuleKey": "wasteland.faction.greenhouse_collective" },
    { "id": "old_world_reclaimers", "nameKey": "wasteland.faction.old_world_reclaimers.name", "typeTags": ["scavenger", "knowledge", "ruins"], "routeTags": ["exploration", "technology", "truth"], "riskLevel": "high", "joinRequirementTags": ["literacy", "repair_skill", "artifact_find"], "creationRequirementTags": ["archive", "technicians", "secure_workshop"], "resourceTags": ["maps", "tools", "old_world_data"], "conflictTags": ["machine_hazard", "corporate_remnant", "raiders"], "startingRelationship": { "attention": [0, 40], "trust": [-15, 25] }, "aiUseRuleKey": "wasteland.faction.old_world_reclaimers" },
    { "id": "white_mask_clinic", "nameKey": "wasteland.faction.white_mask_clinic.name", "typeTags": ["medical", "neutral", "scarce_resource"], "routeTags": ["healing", "mercy", "body_cost"], "riskLevel": "medium", "joinRequirementTags": ["medical_skill", "debt", "rescued_patient"], "creationRequirementTags": ["medicine_stock", "sterile_room", "trained_staff"], "resourceTags": ["medicine", "surgery", "quarantine"], "conflictTags": ["drug_shortage", "mutation_cases", "protection_racket"], "startingRelationship": { "attention": [0, 30], "trust": [0, 25] }, "aiUseRuleKey": "wasteland.faction.white_mask_clinic" },
    { "id": "signal_tower_union", "nameKey": "wasteland.faction.signal_tower_union.name", "typeTags": ["communication", "technician", "neutral"], "routeTags": ["information", "coordination", "politics"], "riskLevel": "medium", "joinRequirementTags": ["radio_skill", "trusted_referral", "maintenance_work"], "creationRequirementTags": ["tower", "power_supply", "operator_network"], "resourceTags": ["radio", "warnings", "messages"], "conflictTags": ["signal_jamming", "propaganda", "tower_siege"], "startingRelationship": { "attention": [0, 35], "trust": [-5, 25] }, "aiUseRuleKey": "wasteland.faction.signal_tower_union" },
    { "id": "ash_pilgrim_order", "nameKey": "wasteland.faction.ash_pilgrim_order.name", "typeTags": ["faith", "pilgrim", "mutant_contact"], "routeTags": ["belief", "adaptation", "mystery"], "riskLevel": "high", "joinRequirementTags": ["radiation_survivor", "vision", "pilgrim_sponsor"], "creationRequirementTags": ["holy_site", "followers", "ritual_code"], "resourceTags": ["shelter", "belief_network", "hazard_lore"], "conflictTags": ["clinic_suspicion", "camp_authority", "mutant_fear"], "startingRelationship": { "attention": [0, 45], "trust": [-20, 20] }, "aiUseRuleKey": "wasteland.faction.ash_pilgrim_order" }
  ]
}
